jupyterlab_ngl/__init__.py
jupyterlab_ngl/_version.py
jupyterlab_ngl/labextension/build_log.json
jupyterlab_ngl/labextension/package.json
jupyterlab_ngl/labextension/static/lib_index_js-webpack_sharing_consume_default_react-dom.485435b50d756bfcfec9.js
jupyterlab_ngl/labextension/static/lib_index_js-webpack_sharing_consume_default_react-dom.485435b50d756bfcfec9.js.map
jupyterlab_ngl/labextension/static/lib_index_js-webpack_sharing_consume_default_react-dom.f5a663ace60f00e74771.js
jupyterlab_ngl/labextension/static/lib_index_js-webpack_sharing_consume_default_react-dom.f5a663ace60f00e74771.js.map
jupyterlab_ngl/labextension/static/remoteEntry.01a2b0aba6a6a34bc34a.js
jupyterlab_ngl/labextension/static/remoteEntry.01a2b0aba6a6a34bc34a.js.map
jupyterlab_ngl/labextension/static/remoteEntry.492a50831495e097a057.js
jupyterlab_ngl/labextension/static/remoteEntry.492a50831495e097a057.js.map
jupyterlab_ngl/labextension/static/style.js
jupyterlab_ngl/labextension/static/style_index_js.a3bdb26ee5ef06eaed06.js
jupyterlab_ngl/labextension/static/style_index_js.a3bdb26ee5ef06eaed06.js.map
jupyterlab_ngl/labextension/static/vendors-node_modules_css-loader_dist_runtime_api_js-node_modules_css-loader_dist_runtime_cssW-926fd9.f810d63834112425d67c.js
jupyterlab_ngl/labextension/static/vendors-node_modules_css-loader_dist_runtime_api_js-node_modules_css-loader_dist_runtime_cssW-926fd9.f810d63834112425d67c.js.map
jupyterlab_ngl/labextension/static/vendors-node_modules_material-ui_core_esm_Box_Box_js-node_modules_material-ui_core_esm_Button-0ab0ba.1173bc9a36d3eb2be065.js
jupyterlab_ngl/labextension/static/vendors-node_modules_material-ui_core_esm_Box_Box_js-node_modules_material-ui_core_esm_Button-0ab0ba.1173bc9a36d3eb2be065.js.map
jupyterlab_ngl/labextension/static/vendors-node_modules_material-ui_core_esm_Box_Box_js-node_modules_material-ui_core_esm_Button-33de0e.5c1f19d6a53914b55bcb.js
jupyterlab_ngl-0.1.5.dist-info/LICENSE
jupyterlab_ngl-0.1.5.dist-info/METADATA
jupyterlab_ngl-0.1.5.dist-info/WHEEL
jupyterlab_ngl-0.1.5.dist-info/top_level.txt
jupyterlab_ngl-0.1.5.dist-info/RECORD
